{
  "ticker": "3576",
  "buyBranches": [
    {
      "broker": "國泰-敦南",
      "buyVol": 1636,
      "sellVol": 450,
      "netBuy": 1186,
      "pct": 3.01
    },
    {
      "broker": "新光",
      "buyVol": 324,
      "sellVol": 20,
      "netBuy": 304,
      "pct": 0.77
    },
    {
      "broker": "元大-苑裡",
      "buyVol": 252,
      "sellVol": 10,
      "netBuy": 242,
      "pct": 0.61
    },
    {
      "broker": "富邦-新板",
      "buyVol": 258,
      "sellVol": 30,
      "netBuy": 228,
      "pct": 0.58
    },
    {
      "broker": "元大-中壢",
      "buyVol": 246,
      "sellVol": 31,
      "netBuy": 215,
      "pct": 0.54
    },
    {
      "broker": "凱基-科園",
      "buyVol": 210,
      "sellVol": 3,
      "netBuy": 207,
      "pct": 0.52
    },
    {
      "broker": "台新-高雄",
      "buyVol": 247,
      "sellVol": 48,
      "netBuy": 199,
      "pct": 0.5
    },
    {
      "broker": "永豐金證券",
      "buyVol": 241,
      "sellVol": 45,
      "netBuy": 196,
      "pct": 0.5
    },
    {
      "broker": "富邦-台北",
      "buyVol": 226,
      "sellVol": 39,
      "netBuy": 187,
      "pct": 0.47
    },
    {
      "broker": "富邦-新竹",
      "buyVol": 202,
      "sellVol": 20,
      "netBuy": 182,
      "pct": 0.46
    },
    {
      "broker": "富邦-板橋",
      "buyVol": 236,
      "sellVol": 56,
      "netBuy": 180,
      "pct": 0.46
    },
    {
      "broker": "永豐金-桃園",
      "buyVol": 182,
      "sellVol": 8,
      "netBuy": 174,
      "pct": 0.44
    },
    {
      "broker": "元大-館前",
      "buyVol": 192,
      "sellVol": 18,
      "netBuy": 174,
      "pct": 0.44
    },
    {
      "broker": "元大-員林中山",
      "buyVol": 171,
      "sellVol": 6,
      "netBuy": 165,
      "pct": 0.42
    },
    {
      "broker": "玉山-高雄",
      "buyVol": 212,
      "sellVol": 48,
      "netBuy": 164,
      "pct": 0.42
    }
  ],
  "sellBranches": [
    {
      "broker": "新加坡商瑞銀",
      "buyVol": 195,
      "sellVol": 7606,
      "netSell": 7411,
      "pct": 18.78
    },
    {
      "broker": "美商高盛",
      "buyVol": 430,
      "sellVol": 4501,
      "netSell": 4071,
      "pct": 10.32
    },
    {
      "broker": "摩根大通",
      "buyVol": 762,
      "sellVol": 3869,
      "netSell": 3107,
      "pct": 7.87
    },
    {
      "broker": "台灣摩根士丹利",
      "buyVol": 435,
      "sellVol": 3007,
      "netSell": 2572,
      "pct": 6.52
    },
    {
      "broker": "凱基-台北",
      "buyVol": 214,
      "sellVol": 2570,
      "netSell": 2356,
      "pct": 5.97
    },
    {
      "broker": "港商野村",
      "buyVol": 0,
      "sellVol": 1479,
      "netSell": 1479,
      "pct": 3.75
    },
    {
      "broker": "元大-竹科",
      "buyVol": 92,
      "sellVol": 918,
      "netSell": 826,
      "pct": 2.09
    },
    {
      "broker": "美林",
      "buyVol": 24,
      "sellVol": 555,
      "netSell": 531,
      "pct": 1.35
    },
    {
      "broker": "國票-台東",
      "buyVol": 32,
      "sellVol": 264,
      "netSell": 232,
      "pct": 0.59
    },
    {
      "broker": "土銀",
      "buyVol": 21,
      "sellVol": 177,
      "netSell": 156,
      "pct": 0.4
    },
    {
      "broker": "統一-內湖",
      "buyVol": 0,
      "sellVol": 138,
      "netSell": 138,
      "pct": 0.35
    },
    {
      "broker": "台新-大昌",
      "buyVol": 47,
      "sellVol": 182,
      "netSell": 135,
      "pct": 0.34
    },
    {
      "broker": "康和-高雄",
      "buyVol": 80,
      "sellVol": 211,
      "netSell": 131,
      "pct": 0.33
    },
    {
      "broker": "合庫-彰化",
      "buyVol": 16,
      "sellVol": 142,
      "netSell": 126,
      "pct": 0.32
    },
    {
      "broker": "富邦-南京",
      "buyVol": 27,
      "sellVol": 149,
      "netSell": 122,
      "pct": 0.31
    }
  ],
  "totalBuyVol": 4002,
  "totalSellVol": 23392,
  "avgBuyCost": 18.26,
  "avgSellCost": 18.23
}