{
  "ticker": "2867",
  "buyBranches": [
    {
      "broker": "美商高盛",
      "buyVol": 2650,
      "sellVol": 355,
      "netBuy": 2295,
      "pct": 19.86
    },
    {
      "broker": "凱基-台北",
      "buyVol": 2036,
      "sellVol": 468,
      "netBuy": 1568,
      "pct": 13.57
    },
    {
      "broker": "亞東-台中",
      "buyVol": 1376,
      "sellVol": 16,
      "netBuy": 1360,
      "pct": 11.77
    },
    {
      "broker": "永豐金證券",
      "buyVol": 973,
      "sellVol": 15,
      "netBuy": 958,
      "pct": 8.29
    },
    {
      "broker": "摩根大通",
      "buyVol": 532,
      "sellVol": 35,
      "netBuy": 497,
      "pct": 4.3
    },
    {
      "broker": "台灣摩根士丹利",
      "buyVol": 782,
      "sellVol": 300,
      "netBuy": 482,
      "pct": 4.17
    },
    {
      "broker": "康和",
      "buyVol": 300,
      "sellVol": 0,
      "netBuy": 300,
      "pct": 2.6
    },
    {
      "broker": "美林",
      "buyVol": 338,
      "sellVol": 91,
      "netBuy": 247,
      "pct": 2.14
    },
    {
      "broker": "國泰-桃園",
      "buyVol": 170,
      "sellVol": 5,
      "netBuy": 165,
      "pct": 1.43
    },
    {
      "broker": "凱基-市政",
      "buyVol": 160,
      "sellVol": 0,
      "netBuy": 160,
      "pct": 1.38
    },
    {
      "broker": "新加坡商瑞銀",
      "buyVol": 193,
      "sellVol": 87,
      "netBuy": 106,
      "pct": 0.92
    },
    {
      "broker": "永豐金-竹科",
      "buyVol": 85,
      "sellVol": 3,
      "netBuy": 82,
      "pct": 0.71
    },
    {
      "broker": "富邦-樹林",
      "buyVol": 80,
      "sellVol": 1,
      "netBuy": 79,
      "pct": 0.68
    },
    {
      "broker": "康和-台中",
      "buyVol": 66,
      "sellVol": 0,
      "netBuy": 66,
      "pct": 0.57
    },
    {
      "broker": "台新-信義",
      "buyVol": 60,
      "sellVol": 0,
      "netBuy": 60,
      "pct": 0.52
    }
  ],
  "sellBranches": [
    {
      "broker": "統一-金門",
      "buyVol": 0,
      "sellVol": 539,
      "netSell": 539,
      "pct": 4.67
    },
    {
      "broker": "群益金鼎-敦南",
      "buyVol": 0,
      "sellVol": 507,
      "netSell": 507,
      "pct": 4.39
    },
    {
      "broker": "凱基-長庚",
      "buyVol": 0,
      "sellVol": 461,
      "netSell": 461,
      "pct": 3.99
    },
    {
      "broker": "台新-中原",
      "buyVol": 0,
      "sellVol": 371,
      "netSell": 371,
      "pct": 3.21
    },
    {
      "broker": "臺銀-臺南",
      "buyVol": 0,
      "sellVol": 342,
      "netSell": 342,
      "pct": 2.96
    },
    {
      "broker": "富邦-仁愛",
      "buyVol": 2,
      "sellVol": 315,
      "netSell": 313,
      "pct": 2.71
    },
    {
      "broker": "統一-員林",
      "buyVol": 0,
      "sellVol": 300,
      "netSell": 300,
      "pct": 2.6
    },
    {
      "broker": "日進",
      "buyVol": 0,
      "sellVol": 222,
      "netSell": 222,
      "pct": 1.92
    },
    {
      "broker": "新光",
      "buyVol": 28,
      "sellVol": 235,
      "netSell": 207,
      "pct": 1.79
    },
    {
      "broker": "華南永昌-豐原",
      "buyVol": 0,
      "sellVol": 200,
      "netSell": 200,
      "pct": 1.73
    },
    {
      "broker": "康和-仁愛",
      "buyVol": 0,
      "sellVol": 186,
      "netSell": 186,
      "pct": 1.61
    },
    {
      "broker": "凱基-高雄",
      "buyVol": 0,
      "sellVol": 160,
      "netSell": 160,
      "pct": 1.38
    },
    {
      "broker": "國票-南港",
      "buyVol": 1,
      "sellVol": 155,
      "netSell": 154,
      "pct": 1.33
    },
    {
      "broker": "元大證券",
      "buyVol": 377,
      "sellVol": 523,
      "netSell": 146,
      "pct": 1.26
    },
    {
      "broker": "台新-台中",
      "buyVol": 3,
      "sellVol": 147,
      "netSell": 144,
      "pct": 1.25
    }
  ],
  "totalBuyVol": 8425,
  "totalSellVol": 4252,
  "avgBuyCost": 8.45,
  "avgSellCost": 8.44
}