{
  "ticker": "2892",
  "buyBranches": [
    {
      "broker": "玉山證券",
      "buyVol": 9861,
      "sellVol": 9,
      "netBuy": 9852,
      "pct": 19.58
    },
    {
      "broker": "富邦證券",
      "buyVol": 4485,
      "sellVol": 13,
      "netBuy": 4472,
      "pct": 8.89
    },
    {
      "broker": "群益金鼎",
      "buyVol": 4524,
      "sellVol": 120,
      "netBuy": 4404,
      "pct": 8.75
    },
    {
      "broker": "台新-大昌",
      "buyVol": 819,
      "sellVol": 12,
      "netBuy": 807,
      "pct": 1.6
    },
    {
      "broker": "土銀",
      "buyVol": 509,
      "sellVol": 0,
      "netBuy": 509,
      "pct": 1.01
    },
    {
      "broker": "國泰-敦南",
      "buyVol": 358,
      "sellVol": 36,
      "netBuy": 322,
      "pct": 0.64
    },
    {
      "broker": "華南永昌-頭份",
      "buyVol": 315,
      "sellVol": 0,
      "netBuy": 315,
      "pct": 0.63
    },
    {
      "broker": "新光",
      "buyVol": 318,
      "sellVol": 8,
      "netBuy": 310,
      "pct": 0.62
    },
    {
      "broker": "台新",
      "buyVol": 278,
      "sellVol": 8,
      "netBuy": 270,
      "pct": 0.54
    },
    {
      "broker": "台新-草屯",
      "buyVol": 250,
      "sellVol": 0,
      "netBuy": 250,
      "pct": 0.5
    },
    {
      "broker": "玉山-高雄",
      "buyVol": 250,
      "sellVol": 6,
      "netBuy": 244,
      "pct": 0.48
    },
    {
      "broker": "臺銀",
      "buyVol": 254,
      "sellVol": 14,
      "netBuy": 240,
      "pct": 0.48
    },
    {
      "broker": "台新-三民",
      "buyVol": 233,
      "sellVol": 0,
      "netBuy": 233,
      "pct": 0.46
    },
    {
      "broker": "元大-莒光",
      "buyVol": 227,
      "sellVol": 2,
      "netBuy": 225,
      "pct": 0.45
    },
    {
      "broker": "第一金-安和",
      "buyVol": 225,
      "sellVol": 0,
      "netBuy": 225,
      "pct": 0.45
    }
  ],
  "sellBranches": [
    {
      "broker": "台灣摩根士丹利",
      "buyVol": 1117,
      "sellVol": 8590,
      "netSell": 7473,
      "pct": 14.85
    },
    {
      "broker": "美商高盛",
      "buyVol": 2997,
      "sellVol": 10396,
      "netSell": 7399,
      "pct": 14.7
    },
    {
      "broker": "美林",
      "buyVol": 606,
      "sellVol": 6650,
      "netSell": 6044,
      "pct": 12.01
    },
    {
      "broker": "凱基",
      "buyVol": 35,
      "sellVol": 2800,
      "netSell": 2765,
      "pct": 5.49
    },
    {
      "broker": "摩根大通",
      "buyVol": 944,
      "sellVol": 3616,
      "netSell": 2672,
      "pct": 5.31
    },
    {
      "broker": "凱基-台北",
      "buyVol": 2771,
      "sellVol": 5082,
      "netSell": 2311,
      "pct": 4.59
    },
    {
      "broker": "花旗環球",
      "buyVol": 682,
      "sellVol": 2100,
      "netSell": 1418,
      "pct": 2.82
    },
    {
      "broker": "新加坡商瑞銀",
      "buyVol": 1591,
      "sellVol": 2572,
      "netSell": 981,
      "pct": 1.95
    },
    {
      "broker": "元大-桃興",
      "buyVol": 1,
      "sellVol": 896,
      "netSell": 895,
      "pct": 1.78
    },
    {
      "broker": "群益金鼎-東大",
      "buyVol": 23,
      "sellVol": 452,
      "netSell": 429,
      "pct": 0.85
    },
    {
      "broker": "元大證券",
      "buyVol": 953,
      "sellVol": 1354,
      "netSell": 401,
      "pct": 0.8
    },
    {
      "broker": "港商野村",
      "buyVol": 53,
      "sellVol": 420,
      "netSell": 367,
      "pct": 0.73
    },
    {
      "broker": "凱基-中壢",
      "buyVol": 2,
      "sellVol": 178,
      "netSell": 176,
      "pct": 0.35
    },
    {
      "broker": "華南永昌-民權",
      "buyVol": 3,
      "sellVol": 100,
      "netSell": 97,
      "pct": 0.19
    },
    {
      "broker": "國票證券",
      "buyVol": 38,
      "sellVol": 119,
      "netSell": 81,
      "pct": 0.16
    }
  ],
  "totalBuyVol": 22678,
  "totalSellVol": 33512,
  "avgBuyCost": 32.33,
  "avgSellCost": 32.33
}