{
  "ticker": "5880",
  "buyBranches": [
    {
      "broker": "美商高盛",
      "buyVol": 7015,
      "sellVol": 670,
      "netBuy": 6345,
      "pct": 13.76
    },
    {
      "broker": "新加坡商瑞銀",
      "buyVol": 6470,
      "sellVol": 1190,
      "netBuy": 5280,
      "pct": 11.45
    },
    {
      "broker": "摩根大通",
      "buyVol": 7883,
      "sellVol": 3396,
      "netBuy": 4487,
      "pct": 9.73
    },
    {
      "broker": "港商麥格理",
      "buyVol": 3142,
      "sellVol": 2,
      "netBuy": 3140,
      "pct": 6.81
    },
    {
      "broker": "台灣摩根士丹利",
      "buyVol": 2955,
      "sellVol": 539,
      "netBuy": 2416,
      "pct": 5.24
    },
    {
      "broker": "臺銀",
      "buyVol": 1677,
      "sellVol": 75,
      "netBuy": 1602,
      "pct": 3.47
    },
    {
      "broker": "永豐金證券",
      "buyVol": 1862,
      "sellVol": 301,
      "netBuy": 1561,
      "pct": 3.38
    },
    {
      "broker": "美林",
      "buyVol": 1343,
      "sellVol": 715,
      "netBuy": 628,
      "pct": 1.36
    },
    {
      "broker": "元大證券",
      "buyVol": 2765,
      "sellVol": 2305,
      "netBuy": 460,
      "pct": 1.0
    },
    {
      "broker": "宏遠證券",
      "buyVol": 273,
      "sellVol": 13,
      "netBuy": 260,
      "pct": 0.56
    },
    {
      "broker": "富邦證券",
      "buyVol": 274,
      "sellVol": 26,
      "netBuy": 248,
      "pct": 0.54
    },
    {
      "broker": "凱基",
      "buyVol": 300,
      "sellVol": 73,
      "netBuy": 227,
      "pct": 0.49
    },
    {
      "broker": "第一金",
      "buyVol": 222,
      "sellVol": 10,
      "netBuy": 212,
      "pct": 0.46
    },
    {
      "broker": "華南永昌",
      "buyVol": 273,
      "sellVol": 76,
      "netBuy": 197,
      "pct": 0.43
    },
    {
      "broker": "統一",
      "buyVol": 158,
      "sellVol": 7,
      "netBuy": 151,
      "pct": 0.33
    }
  ],
  "sellBranches": [
    {
      "broker": "國泰-敦南",
      "buyVol": 34,
      "sellVol": 993,
      "netSell": 959,
      "pct": 2.08
    },
    {
      "broker": "第一金-新竹",
      "buyVol": 0,
      "sellVol": 666,
      "netSell": 666,
      "pct": 1.44
    },
    {
      "broker": "合庫-台南",
      "buyVol": 4,
      "sellVol": 455,
      "netSell": 451,
      "pct": 0.98
    },
    {
      "broker": "凱基-基隆",
      "buyVol": 11,
      "sellVol": 426,
      "netSell": 415,
      "pct": 0.9
    },
    {
      "broker": "玉山-大里",
      "buyVol": 11,
      "sellVol": 401,
      "netSell": 390,
      "pct": 0.85
    },
    {
      "broker": "國泰-板橋",
      "buyVol": 2,
      "sellVol": 388,
      "netSell": 386,
      "pct": 0.84
    },
    {
      "broker": "富邦-新店",
      "buyVol": 31,
      "sellVol": 398,
      "netSell": 367,
      "pct": 0.8
    },
    {
      "broker": "凱基-台北",
      "buyVol": 1850,
      "sellVol": 2214,
      "netSell": 364,
      "pct": 0.79
    },
    {
      "broker": "元大-佳里",
      "buyVol": 10,
      "sellVol": 340,
      "netSell": 330,
      "pct": 0.72
    },
    {
      "broker": "臺銀-臺中",
      "buyVol": 2,
      "sellVol": 317,
      "netSell": 315,
      "pct": 0.68
    },
    {
      "broker": "合庫-台中",
      "buyVol": 18,
      "sellVol": 321,
      "netSell": 303,
      "pct": 0.66
    },
    {
      "broker": "花旗環球",
      "buyVol": 975,
      "sellVol": 1262,
      "netSell": 287,
      "pct": 0.62
    },
    {
      "broker": "富邦-高雄",
      "buyVol": 3,
      "sellVol": 283,
      "netSell": 280,
      "pct": 0.61
    },
    {
      "broker": "凱基-五股",
      "buyVol": 3,
      "sellVol": 280,
      "netSell": 277,
      "pct": 0.6
    },
    {
      "broker": "元大-成功",
      "buyVol": 2,
      "sellVol": 277,
      "netSell": 275,
      "pct": 0.6
    }
  ],
  "totalBuyVol": 27215,
  "totalSellVol": 6065,
  "avgBuyCost": 23.8,
  "avgSellCost": 23.79
}