{
  "ticker": "1802",
  "buyBranches": [
    {
      "broker": "美商高盛",
      "buyVol": 5563,
      "sellVol": 1486,
      "netBuy": 4077,
      "pct": 9.56
    },
    {
      "broker": "凱基-台北",
      "buyVol": 5114,
      "sellVol": 4158,
      "netBuy": 956,
      "pct": 2.24
    },
    {
      "broker": "港商野村",
      "buyVol": 873,
      "sellVol": 57,
      "netBuy": 816,
      "pct": 1.91
    },
    {
      "broker": "永豐金證券",
      "buyVol": 942,
      "sellVol": 149,
      "netBuy": 793,
      "pct": 1.86
    },
    {
      "broker": "國泰證券",
      "buyVol": 495,
      "sellVol": 53,
      "netBuy": 442,
      "pct": 1.04
    },
    {
      "broker": "富邦-南屯",
      "buyVol": 409,
      "sellVol": 26,
      "netBuy": 383,
      "pct": 0.9
    },
    {
      "broker": "群益金鼎",
      "buyVol": 533,
      "sellVol": 339,
      "netBuy": 194,
      "pct": 0.46
    },
    {
      "broker": "花旗環球",
      "buyVol": 120,
      "sellVol": 14,
      "netBuy": 106,
      "pct": 0.25
    },
    {
      "broker": "華南永昌-民權",
      "buyVol": 106,
      "sellVol": 9,
      "netBuy": 97,
      "pct": 0.23
    },
    {
      "broker": "元大證券",
      "buyVol": 4547,
      "sellVol": 4474,
      "netBuy": 73,
      "pct": 0.17
    },
    {
      "broker": "盈溢-楠梓",
      "buyVol": 70,
      "sellVol": 0,
      "netBuy": 70,
      "pct": 0.16
    },
    {
      "broker": "兆豐-高雄",
      "buyVol": 77,
      "sellVol": 13,
      "netBuy": 64,
      "pct": 0.15
    },
    {
      "broker": "元大-佳里",
      "buyVol": 66,
      "sellVol": 26,
      "netBuy": 40,
      "pct": 0.09
    },
    {
      "broker": "群益金鼎-南京",
      "buyVol": 43,
      "sellVol": 5,
      "netBuy": 38,
      "pct": 0.09
    },
    {
      "broker": "富邦-仁愛",
      "buyVol": 219,
      "sellVol": 187,
      "netBuy": 32,
      "pct": 0.08
    }
  ],
  "sellBranches": [
    {
      "broker": "摩根大通",
      "buyVol": 451,
      "sellVol": 1579,
      "netSell": 1128,
      "pct": 2.65
    },
    {
      "broker": "華南永昌-忠孝",
      "buyVol": 1,
      "sellVol": 802,
      "netSell": 801,
      "pct": 1.88
    },
    {
      "broker": "台灣摩根士丹利",
      "buyVol": 797,
      "sellVol": 1298,
      "netSell": 501,
      "pct": 1.18
    },
    {
      "broker": "富邦-桃園",
      "buyVol": 26,
      "sellVol": 283,
      "netSell": 257,
      "pct": 0.6
    },
    {
      "broker": "元大-北屯",
      "buyVol": 50,
      "sellVol": 258,
      "netSell": 208,
      "pct": 0.49
    },
    {
      "broker": "新加坡商瑞銀",
      "buyVol": 699,
      "sellVol": 902,
      "netSell": 203,
      "pct": 0.48
    },
    {
      "broker": "永豐金-南投",
      "buyVol": 2,
      "sellVol": 200,
      "netSell": 198,
      "pct": 0.46
    },
    {
      "broker": "國泰-敦南",
      "buyVol": 1454,
      "sellVol": 1643,
      "netSell": 189,
      "pct": 0.44
    },
    {
      "broker": "國泰-板橋",
      "buyVol": 129,
      "sellVol": 314,
      "netSell": 185,
      "pct": 0.43
    },
    {
      "broker": "統一",
      "buyVol": 86,
      "sellVol": 229,
      "netSell": 143,
      "pct": 0.34
    },
    {
      "broker": "群益金鼎-大甲",
      "buyVol": 5,
      "sellVol": 122,
      "netSell": 117,
      "pct": 0.27
    },
    {
      "broker": "凱基-桃園",
      "buyVol": 22,
      "sellVol": 136,
      "netSell": 114,
      "pct": 0.27
    },
    {
      "broker": "國泰-桃園",
      "buyVol": 163,
      "sellVol": 267,
      "netSell": 104,
      "pct": 0.24
    },
    {
      "broker": "元大-草屯",
      "buyVol": 62,
      "sellVol": 165,
      "netSell": 103,
      "pct": 0.24
    },
    {
      "broker": "台新-大裕",
      "buyVol": 10,
      "sellVol": 113,
      "netSell": 103,
      "pct": 0.24
    }
  ],
  "totalBuyVol": 8181,
  "totalSellVol": 4354,
  "avgBuyCost": 67.72,
  "avgSellCost": 67.54
}