{
  "ticker": "2801",
  "buyBranches": [
    {
      "broker": "摩根大通",
      "buyVol": 5957,
      "sellVol": 798,
      "netBuy": 5159,
      "pct": 18.34
    },
    {
      "broker": "台灣摩根士丹利",
      "buyVol": 4833,
      "sellVol": 5,
      "netBuy": 4828,
      "pct": 17.16
    },
    {
      "broker": "美林",
      "buyVol": 3028,
      "sellVol": 35,
      "netBuy": 2993,
      "pct": 10.64
    },
    {
      "broker": "美商高盛",
      "buyVol": 2593,
      "sellVol": 318,
      "netBuy": 2275,
      "pct": 8.09
    },
    {
      "broker": "港商野村",
      "buyVol": 1305,
      "sellVol": 0,
      "netBuy": 1305,
      "pct": 4.64
    },
    {
      "broker": "永豐金-板新",
      "buyVol": 1007,
      "sellVol": 66,
      "netBuy": 941,
      "pct": 3.34
    },
    {
      "broker": "凱基-台北",
      "buyVol": 2040,
      "sellVol": 1176,
      "netBuy": 864,
      "pct": 3.07
    },
    {
      "broker": "華南永昌",
      "buyVol": 838,
      "sellVol": 36,
      "netBuy": 802,
      "pct": 2.85
    },
    {
      "broker": "元大證券",
      "buyVol": 1310,
      "sellVol": 622,
      "netBuy": 688,
      "pct": 2.45
    },
    {
      "broker": "新加坡商瑞銀",
      "buyVol": 1093,
      "sellVol": 596,
      "netBuy": 497,
      "pct": 1.77
    },
    {
      "broker": "統一-敦南",
      "buyVol": 285,
      "sellVol": 16,
      "netBuy": 269,
      "pct": 0.96
    },
    {
      "broker": "富邦證券",
      "buyVol": 219,
      "sellVol": 21,
      "netBuy": 198,
      "pct": 0.7
    },
    {
      "broker": "永豐金-台南",
      "buyVol": 108,
      "sellVol": 8,
      "netBuy": 100,
      "pct": 0.36
    },
    {
      "broker": "兆豐-城中",
      "buyVol": 100,
      "sellVol": 1,
      "netBuy": 99,
      "pct": 0.35
    },
    {
      "broker": "元大-大安",
      "buyVol": 100,
      "sellVol": 8,
      "netBuy": 92,
      "pct": 0.33
    }
  ],
  "sellBranches": [
    {
      "broker": "元大-內湖民權",
      "buyVol": 2,
      "sellVol": 1004,
      "netSell": 1002,
      "pct": 3.56
    },
    {
      "broker": "第一金-新興",
      "buyVol": 10,
      "sellVol": 790,
      "netSell": 780,
      "pct": 2.77
    },
    {
      "broker": "第一金-安和",
      "buyVol": 0,
      "sellVol": 701,
      "netSell": 701,
      "pct": 2.49
    },
    {
      "broker": "華南永昌-中正",
      "buyVol": 2,
      "sellVol": 695,
      "netSell": 693,
      "pct": 2.46
    },
    {
      "broker": "臺銀-臺南",
      "buyVol": 9,
      "sellVol": 620,
      "netSell": 611,
      "pct": 2.17
    },
    {
      "broker": "國泰-敦南",
      "buyVol": 76,
      "sellVol": 644,
      "netSell": 568,
      "pct": 2.02
    },
    {
      "broker": "台新-中港",
      "buyVol": 0,
      "sellVol": 502,
      "netSell": 502,
      "pct": 1.78
    },
    {
      "broker": "富邦-竹北",
      "buyVol": 10,
      "sellVol": 435,
      "netSell": 425,
      "pct": 1.51
    },
    {
      "broker": "國泰-桃園",
      "buyVol": 4,
      "sellVol": 417,
      "netSell": 413,
      "pct": 1.47
    },
    {
      "broker": "新光",
      "buyVol": 57,
      "sellVol": 409,
      "netSell": 352,
      "pct": 1.25
    },
    {
      "broker": "富邦-永和",
      "buyVol": 0,
      "sellVol": 285,
      "netSell": 285,
      "pct": 1.01
    },
    {
      "broker": "彰銀-台中",
      "buyVol": 5,
      "sellVol": 281,
      "netSell": 276,
      "pct": 0.98
    },
    {
      "broker": "永豐金-古亭",
      "buyVol": 0,
      "sellVol": 270,
      "netSell": 270,
      "pct": 0.96
    },
    {
      "broker": "元大-三民",
      "buyVol": 8,
      "sellVol": 261,
      "netSell": 253,
      "pct": 0.9
    },
    {
      "broker": "彰銀",
      "buyVol": 8,
      "sellVol": 239,
      "netSell": 231,
      "pct": 0.82
    }
  ],
  "totalBuyVol": 21109,
  "totalSellVol": 7361,
  "avgBuyCost": 23.1,
  "avgSellCost": 23.11
}