{
  "ticker": "1402",
  "buyBranches": [
    {
      "broker": "元大證券",
      "buyVol": 28342,
      "sellVol": 4001,
      "netBuy": 24341,
      "pct": 25.11
    },
    {
      "broker": "美商高盛",
      "buyVol": 4968,
      "sellVol": 970,
      "netBuy": 3998,
      "pct": 4.12
    },
    {
      "broker": "香港上海匯豐",
      "buyVol": 3597,
      "sellVol": 0,
      "netBuy": 3597,
      "pct": 3.71
    },
    {
      "broker": "群益金鼎",
      "buyVol": 2713,
      "sellVol": 93,
      "netBuy": 2620,
      "pct": 2.7
    },
    {
      "broker": "美林",
      "buyVol": 2456,
      "sellVol": 499,
      "netBuy": 1957,
      "pct": 2.02
    },
    {
      "broker": "港商野村",
      "buyVol": 1315,
      "sellVol": 119,
      "netBuy": 1196,
      "pct": 1.23
    },
    {
      "broker": "花旗環球",
      "buyVol": 1146,
      "sellVol": 0,
      "netBuy": 1146,
      "pct": 1.18
    },
    {
      "broker": "新加坡商瑞銀",
      "buyVol": 7726,
      "sellVol": 6713,
      "netBuy": 1013,
      "pct": 1.05
    },
    {
      "broker": "統一",
      "buyVol": 1019,
      "sellVol": 111,
      "netBuy": 908,
      "pct": 0.94
    },
    {
      "broker": "群益金鼎-瑞豐",
      "buyVol": 693,
      "sellVol": 32,
      "netBuy": 661,
      "pct": 0.68
    },
    {
      "broker": "元大-西螺",
      "buyVol": 304,
      "sellVol": 1,
      "netBuy": 303,
      "pct": 0.31
    },
    {
      "broker": "玉山-新莊",
      "buyVol": 265,
      "sellVol": 79,
      "netBuy": 186,
      "pct": 0.19
    },
    {
      "broker": "台新-建北",
      "buyVol": 203,
      "sellVol": 21,
      "netBuy": 182,
      "pct": 0.19
    },
    {
      "broker": "富邦-羅東",
      "buyVol": 200,
      "sellVol": 23,
      "netBuy": 177,
      "pct": 0.18
    },
    {
      "broker": "國票-九鼎",
      "buyVol": 191,
      "sellVol": 26,
      "netBuy": 165,
      "pct": 0.17
    }
  ],
  "sellBranches": [
    {
      "broker": "凱基",
      "buyVol": 2,
      "sellVol": 12009,
      "netSell": 12007,
      "pct": 12.39
    },
    {
      "broker": "永豐金證券",
      "buyVol": 224,
      "sellVol": 12196,
      "netSell": 11972,
      "pct": 12.35
    },
    {
      "broker": "凱基-台北",
      "buyVol": 5934,
      "sellVol": 9370,
      "netSell": 3436,
      "pct": 3.54
    },
    {
      "broker": "台灣摩根士丹利",
      "buyVol": 5035,
      "sellVol": 6074,
      "netSell": 1039,
      "pct": 1.07
    },
    {
      "broker": "台新-中港",
      "buyVol": 1,
      "sellVol": 681,
      "netSell": 680,
      "pct": 0.7
    },
    {
      "broker": "新光",
      "buyVol": 605,
      "sellVol": 1120,
      "netSell": 515,
      "pct": 0.53
    },
    {
      "broker": "亞東",
      "buyVol": 226,
      "sellVol": 732,
      "netSell": 506,
      "pct": 0.52
    },
    {
      "broker": "臺銀-金山",
      "buyVol": 6,
      "sellVol": 492,
      "netSell": 486,
      "pct": 0.5
    },
    {
      "broker": "國泰-敦南",
      "buyVol": 525,
      "sellVol": 1008,
      "netSell": 483,
      "pct": 0.5
    },
    {
      "broker": "元大-員林",
      "buyVol": 54,
      "sellVol": 506,
      "netSell": 452,
      "pct": 0.47
    },
    {
      "broker": "台新",
      "buyVol": 71,
      "sellVol": 506,
      "netSell": 435,
      "pct": 0.45
    },
    {
      "broker": "台新-虎尾",
      "buyVol": 250,
      "sellVol": 678,
      "netSell": 428,
      "pct": 0.44
    },
    {
      "broker": "統一-彰化",
      "buyVol": 51,
      "sellVol": 417,
      "netSell": 366,
      "pct": 0.38
    },
    {
      "broker": "永豐金-松山",
      "buyVol": 0,
      "sellVol": 340,
      "netSell": 340,
      "pct": 0.35
    },
    {
      "broker": "華南永昌-鳳山",
      "buyVol": 97,
      "sellVol": 328,
      "netSell": 231,
      "pct": 0.24
    }
  ],
  "totalBuyVol": 42450,
  "totalSellVol": 33378,
  "avgBuyCost": 27.31,
  "avgSellCost": 27.27
}