{
  "fetched_at": "2026-06-12T21:31:48+08:00",
  "date": "2026-06-12",
  "taiex": {
    "close": 44169.04,
    "change": 1019.58,
    "change_pct": 2.36,
    "volume_b_ntd": null,
    "source": "twse-MI_INDEX-tables"
  },
  "tx_futures": {
    "close": 44188.0,
    "change": 969.0,
    "open_interest": 71366.0,
    "oi_change": null,
    "volume": 80412.0,
    "source": "taifex-csv",
    "basis": 18.96
  },
  "institutional_futures": {
    "source": "taifex-csv",
    "dealer": {
      "net_oi": 3568,
      "oi_change": null
    },
    "investment_trust": {
      "net_oi": 57111,
      "oi_change": null
    },
    "foreign": {
      "net_oi": -65039,
      "oi_change": null
    }
  },
  "errors": []
}