{
  "ticker": "2406",
  "buyBranches": [
    {
      "broker": "富邦證券",
      "buyVol": 6401,
      "sellVol": 417,
      "netBuy": 5984,
      "pct": 8.85
    },
    {
      "broker": "美商高盛",
      "buyVol": 3779,
      "sellVol": 1955,
      "netBuy": 1824,
      "pct": 2.7
    },
    {
      "broker": "摩根大通",
      "buyVol": 2599,
      "sellVol": 1225,
      "netBuy": 1374,
      "pct": 2.03
    },
    {
      "broker": "港商野村",
      "buyVol": 1930,
      "sellVol": 612,
      "netBuy": 1318,
      "pct": 1.95
    },
    {
      "broker": "台灣摩根士丹利",
      "buyVol": 2068,
      "sellVol": 1167,
      "netBuy": 901,
      "pct": 1.33
    },
    {
      "broker": "富邦-嘉義",
      "buyVol": 819,
      "sellVol": 142,
      "netBuy": 677,
      "pct": 1.0
    },
    {
      "broker": "新加坡商瑞銀",
      "buyVol": 1248,
      "sellVol": 648,
      "netBuy": 600,
      "pct": 0.89
    },
    {
      "broker": "凱基-豐中",
      "buyVol": 580,
      "sellVol": 45,
      "netBuy": 535,
      "pct": 0.79
    },
    {
      "broker": "元大-館前",
      "buyVol": 503,
      "sellVol": 66,
      "netBuy": 437,
      "pct": 0.65
    },
    {
      "broker": "國票-敦北法人",
      "buyVol": 289,
      "sellVol": 10,
      "netBuy": 279,
      "pct": 0.41
    },
    {
      "broker": "玉山-台南",
      "buyVol": 471,
      "sellVol": 208,
      "netBuy": 263,
      "pct": 0.39
    },
    {
      "broker": "統一-南京",
      "buyVol": 417,
      "sellVol": 172,
      "netBuy": 245,
      "pct": 0.36
    },
    {
      "broker": "高橋-中壢",
      "buyVol": 170,
      "sellVol": 0,
      "netBuy": 170,
      "pct": 0.25
    },
    {
      "broker": "華南永昌",
      "buyVol": 764,
      "sellVol": 599,
      "netBuy": 165,
      "pct": 0.24
    },
    {
      "broker": "永豐金-高雄",
      "buyVol": 152,
      "sellVol": 31,
      "netBuy": 121,
      "pct": 0.18
    }
  ],
  "sellBranches": [
    {
      "broker": "凱基-台北",
      "buyVol": 2497,
      "sellVol": 3722,
      "netSell": 1225,
      "pct": 1.81
    },
    {
      "broker": "統一",
      "buyVol": 70,
      "sellVol": 1288,
      "netSell": 1218,
      "pct": 1.8
    },
    {
      "broker": "永豐金-信義",
      "buyVol": 6,
      "sellVol": 463,
      "netSell": 457,
      "pct": 0.68
    },
    {
      "broker": "統一-新竹",
      "buyVol": 14,
      "sellVol": 413,
      "netSell": 399,
      "pct": 0.59
    },
    {
      "broker": "兆豐-南門",
      "buyVol": 26,
      "sellVol": 332,
      "netSell": 306,
      "pct": 0.45
    },
    {
      "broker": "新光",
      "buyVol": 319,
      "sellVol": 581,
      "netSell": 262,
      "pct": 0.39
    },
    {
      "broker": "華南永昌-彰化",
      "buyVol": 37,
      "sellVol": 280,
      "netSell": 243,
      "pct": 0.36
    },
    {
      "broker": "美林",
      "buyVol": 565,
      "sellVol": 808,
      "netSell": 243,
      "pct": 0.36
    },
    {
      "broker": "大昌-樹林",
      "buyVol": 45,
      "sellVol": 283,
      "netSell": 238,
      "pct": 0.35
    },
    {
      "broker": "台新-世貿",
      "buyVol": 24,
      "sellVol": 251,
      "netSell": 227,
      "pct": 0.34
    },
    {
      "broker": "(牛牛牛)亞-鑫豐",
      "buyVol": 32,
      "sellVol": 228,
      "netSell": 196,
      "pct": 0.29
    },
    {
      "broker": "永興-大墩",
      "buyVol": 5,
      "sellVol": 201,
      "netSell": 196,
      "pct": 0.29
    },
    {
      "broker": "玉山-桃園",
      "buyVol": 35,
      "sellVol": 230,
      "netSell": 195,
      "pct": 0.29
    },
    {
      "broker": "群益金鼎-土城",
      "buyVol": 22,
      "sellVol": 184,
      "netSell": 162,
      "pct": 0.24
    },
    {
      "broker": "富邦-永和",
      "buyVol": 72,
      "sellVol": 207,
      "netSell": 135,
      "pct": 0.2
    }
  ],
  "totalBuyVol": 14893,
  "totalSellVol": 5702,
  "avgBuyCost": 38.61,
  "avgSellCost": 37.53
}