{
  "ticker": "2610",
  "buyBranches": [
    {
      "broker": "台灣摩根士丹利",
      "buyVol": 15237,
      "sellVol": 1311,
      "netBuy": 13926,
      "pct": 17.56
    },
    {
      "broker": "美商高盛",
      "buyVol": 9945,
      "sellVol": 254,
      "netBuy": 9691,
      "pct": 12.22
    },
    {
      "broker": "新加坡商瑞銀",
      "buyVol": 5285,
      "sellVol": 836,
      "netBuy": 4449,
      "pct": 5.61
    },
    {
      "broker": "摩根大通",
      "buyVol": 5072,
      "sellVol": 906,
      "netBuy": 4166,
      "pct": 5.25
    },
    {
      "broker": "美林",
      "buyVol": 3607,
      "sellVol": 128,
      "netBuy": 3479,
      "pct": 4.39
    },
    {
      "broker": "凱基-台北",
      "buyVol": 6729,
      "sellVol": 3275,
      "netBuy": 3454,
      "pct": 4.36
    },
    {
      "broker": "元大證券",
      "buyVol": 8433,
      "sellVol": 5352,
      "netBuy": 3081,
      "pct": 3.89
    },
    {
      "broker": "臺銀",
      "buyVol": 2537,
      "sellVol": 56,
      "netBuy": 2481,
      "pct": 3.13
    },
    {
      "broker": "大和國泰",
      "buyVol": 1792,
      "sellVol": 0,
      "netBuy": 1792,
      "pct": 2.26
    },
    {
      "broker": "中國信託",
      "buyVol": 1646,
      "sellVol": 248,
      "netBuy": 1398,
      "pct": 1.76
    },
    {
      "broker": "永豐金-內湖",
      "buyVol": 451,
      "sellVol": 11,
      "netBuy": 440,
      "pct": 0.55
    },
    {
      "broker": "凱基",
      "buyVol": 426,
      "sellVol": 5,
      "netBuy": 421,
      "pct": 0.53
    },
    {
      "broker": "華南永昌-世貿",
      "buyVol": 302,
      "sellVol": 11,
      "netBuy": 291,
      "pct": 0.37
    },
    {
      "broker": "華南永昌-中正",
      "buyVol": 305,
      "sellVol": 22,
      "netBuy": 283,
      "pct": 0.36
    },
    {
      "broker": "台新-基隆",
      "buyVol": 270,
      "sellVol": 27,
      "netBuy": 243,
      "pct": 0.31
    }
  ],
  "sellBranches": [
    {
      "broker": "國泰-敦南",
      "buyVol": 391,
      "sellVol": 2159,
      "netSell": 1768,
      "pct": 2.23
    },
    {
      "broker": "凱基-站前",
      "buyVol": 31,
      "sellVol": 902,
      "netSell": 871,
      "pct": 1.1
    },
    {
      "broker": "中國信託-高雄",
      "buyVol": 13,
      "sellVol": 780,
      "netSell": 767,
      "pct": 0.97
    },
    {
      "broker": "新光",
      "buyVol": 32,
      "sellVol": 797,
      "netSell": 765,
      "pct": 0.96
    },
    {
      "broker": "台灣企銀-桃園",
      "buyVol": 2,
      "sellVol": 736,
      "netSell": 734,
      "pct": 0.93
    },
    {
      "broker": "富邦-公益",
      "buyVol": 9,
      "sellVol": 649,
      "netSell": 640,
      "pct": 0.81
    },
    {
      "broker": "元大-中壢",
      "buyVol": 43,
      "sellVol": 678,
      "netSell": 635,
      "pct": 0.8
    },
    {
      "broker": "台新-高雄",
      "buyVol": 28,
      "sellVol": 640,
      "netSell": 612,
      "pct": 0.77
    },
    {
      "broker": "台新",
      "buyVol": 286,
      "sellVol": 851,
      "netSell": 565,
      "pct": 0.71
    },
    {
      "broker": "台灣企銀-九如",
      "buyVol": 1,
      "sellVol": 542,
      "netSell": 541,
      "pct": 0.68
    },
    {
      "broker": "國泰-台中",
      "buyVol": 105,
      "sellVol": 632,
      "netSell": 527,
      "pct": 0.66
    },
    {
      "broker": "元大-東泰",
      "buyVol": 110,
      "sellVol": 601,
      "netSell": 491,
      "pct": 0.62
    },
    {
      "broker": "富邦-台北",
      "buyVol": 70,
      "sellVol": 554,
      "netSell": 484,
      "pct": 0.61
    },
    {
      "broker": "臺銀-臺中",
      "buyVol": 199,
      "sellVol": 637,
      "netSell": 438,
      "pct": 0.55
    },
    {
      "broker": "凱基-桃園",
      "buyVol": 14,
      "sellVol": 445,
      "netSell": 431,
      "pct": 0.54
    }
  ],
  "totalBuyVol": 49595,
  "totalSellVol": 10269,
  "avgBuyCost": 20.36,
  "avgSellCost": 20.35
}