{
  "ticker": "8033",
  "buyBranches": [
    {
      "broker": "美商高盛",
      "buyVol": 3996,
      "sellVol": 1320,
      "netBuy": 2676,
      "pct": 5.04
    },
    {
      "broker": "台灣摩根士丹利",
      "buyVol": 2338,
      "sellVol": 373,
      "netBuy": 1965,
      "pct": 3.7
    },
    {
      "broker": "新加坡商瑞銀",
      "buyVol": 1074,
      "sellVol": 413,
      "netBuy": 661,
      "pct": 1.25
    },
    {
      "broker": "華南永昌-中正",
      "buyVol": 591,
      "sellVol": 234,
      "netBuy": 357,
      "pct": 0.67
    },
    {
      "broker": "摩根大通",
      "buyVol": 1168,
      "sellVol": 892,
      "netBuy": 276,
      "pct": 0.52
    },
    {
      "broker": "新光-台中",
      "buyVol": 287,
      "sellVol": 172,
      "netBuy": 115,
      "pct": 0.22
    },
    {
      "broker": "凱基-科園",
      "buyVol": 115,
      "sellVol": 6,
      "netBuy": 109,
      "pct": 0.21
    },
    {
      "broker": "大昌",
      "buyVol": 126,
      "sellVol": 23,
      "netBuy": 103,
      "pct": 0.19
    },
    {
      "broker": "元大-南屯",
      "buyVol": 168,
      "sellVol": 68,
      "netBuy": 100,
      "pct": 0.19
    },
    {
      "broker": "台新-同大",
      "buyVol": 131,
      "sellVol": 52,
      "netBuy": 79,
      "pct": 0.15
    },
    {
      "broker": "國泰-台中",
      "buyVol": 473,
      "sellVol": 398,
      "netBuy": 75,
      "pct": 0.14
    },
    {
      "broker": "台新-板橋",
      "buyVol": 99,
      "sellVol": 30,
      "netBuy": 69,
      "pct": 0.13
    },
    {
      "broker": "統一-台中",
      "buyVol": 157,
      "sellVol": 92,
      "netBuy": 65,
      "pct": 0.12
    },
    {
      "broker": "新百王",
      "buyVol": 298,
      "sellVol": 234,
      "netBuy": 64,
      "pct": 0.12
    },
    {
      "broker": "元大-天母",
      "buyVol": 92,
      "sellVol": 33,
      "netBuy": 59,
      "pct": 0.11
    }
  ],
  "sellBranches": [
    {
      "broker": "元大證券",
      "buyVol": 5343,
      "sellVol": 8608,
      "netSell": 3265,
      "pct": 6.15
    },
    {
      "broker": "凱基-台北",
      "buyVol": 2922,
      "sellVol": 3770,
      "netSell": 848,
      "pct": 1.6
    },
    {
      "broker": "港商野村",
      "buyVol": 155,
      "sellVol": 689,
      "netSell": 534,
      "pct": 1.01
    },
    {
      "broker": "美林",
      "buyVol": 215,
      "sellVol": 618,
      "netSell": 403,
      "pct": 0.76
    },
    {
      "broker": "富邦證券",
      "buyVol": 64,
      "sellVol": 464,
      "netSell": 400,
      "pct": 0.75
    },
    {
      "broker": "群益金鼎",
      "buyVol": 142,
      "sellVol": 491,
      "netSell": 349,
      "pct": 0.66
    },
    {
      "broker": "永豐金-市政",
      "buyVol": 67,
      "sellVol": 393,
      "netSell": 326,
      "pct": 0.61
    },
    {
      "broker": "中國信託-高雄",
      "buyVol": 133,
      "sellVol": 408,
      "netSell": 275,
      "pct": 0.52
    },
    {
      "broker": "凱基",
      "buyVol": 37,
      "sellVol": 263,
      "netSell": 226,
      "pct": 0.43
    },
    {
      "broker": "凱基-城中",
      "buyVol": 21,
      "sellVol": 237,
      "netSell": 216,
      "pct": 0.41
    },
    {
      "broker": "凱基-站前",
      "buyVol": 36,
      "sellVol": 190,
      "netSell": 154,
      "pct": 0.29
    },
    {
      "broker": "國票-敦北法人",
      "buyVol": 20,
      "sellVol": 137,
      "netSell": 117,
      "pct": 0.22
    },
    {
      "broker": "元大-北屯",
      "buyVol": 50,
      "sellVol": 152,
      "netSell": 102,
      "pct": 0.19
    },
    {
      "broker": "元大-太平",
      "buyVol": 39,
      "sellVol": 133,
      "netSell": 94,
      "pct": 0.18
    },
    {
      "broker": "統一",
      "buyVol": 103,
      "sellVol": 195,
      "netSell": 92,
      "pct": 0.17
    }
  ],
  "totalBuyVol": 6774,
  "totalSellVol": 7401,
  "avgBuyCost": 188.25,
  "avgSellCost": 189.39
}