{
  "ticker": "5880",
  "buyBranches": [
    {
      "broker": "元大證券",
      "buyVol": 12866,
      "sellVol": 1102,
      "netBuy": 11764,
      "pct": 24.85
    },
    {
      "broker": "摩根大通",
      "buyVol": 7997,
      "sellVol": 1965,
      "netBuy": 6032,
      "pct": 12.74
    },
    {
      "broker": "台灣摩根士丹利",
      "buyVol": 5890,
      "sellVol": 199,
      "netBuy": 5691,
      "pct": 12.02
    },
    {
      "broker": "美商高盛",
      "buyVol": 5535,
      "sellVol": 701,
      "netBuy": 4834,
      "pct": 10.21
    },
    {
      "broker": "新加坡商瑞銀",
      "buyVol": 3781,
      "sellVol": 688,
      "netBuy": 3093,
      "pct": 6.53
    },
    {
      "broker": "凱基-台北",
      "buyVol": 3057,
      "sellVol": 1534,
      "netBuy": 1523,
      "pct": 3.22
    },
    {
      "broker": "元大-林森",
      "buyVol": 1150,
      "sellVol": 29,
      "netBuy": 1121,
      "pct": 2.37
    },
    {
      "broker": "花旗環球",
      "buyVol": 1037,
      "sellVol": 272,
      "netBuy": 765,
      "pct": 1.62
    },
    {
      "broker": "合庫-自強",
      "buyVol": 502,
      "sellVol": 146,
      "netBuy": 356,
      "pct": 0.75
    },
    {
      "broker": "美林",
      "buyVol": 1371,
      "sellVol": 1069,
      "netBuy": 302,
      "pct": 0.64
    },
    {
      "broker": "兆豐-南門",
      "buyVol": 200,
      "sellVol": 1,
      "netBuy": 199,
      "pct": 0.42
    },
    {
      "broker": "凱基-埔墘",
      "buyVol": 200,
      "sellVol": 13,
      "netBuy": 187,
      "pct": 0.4
    },
    {
      "broker": "第一金",
      "buyVol": 162,
      "sellVol": 0,
      "netBuy": 162,
      "pct": 0.34
    },
    {
      "broker": "永豐金證券",
      "buyVol": 348,
      "sellVol": 189,
      "netBuy": 159,
      "pct": 0.34
    },
    {
      "broker": "元大-南投",
      "buyVol": 96,
      "sellVol": 40,
      "netBuy": 56,
      "pct": 0.12
    }
  ],
  "sellBranches": [
    {
      "broker": "合庫證券",
      "buyVol": 21,
      "sellVol": 1137,
      "netSell": 1116,
      "pct": 2.36
    },
    {
      "broker": "群益金鼎-南京",
      "buyVol": 31,
      "sellVol": 858,
      "netSell": 827,
      "pct": 1.75
    },
    {
      "broker": "國泰-敦南",
      "buyVol": 60,
      "sellVol": 863,
      "netSell": 803,
      "pct": 1.7
    },
    {
      "broker": "合庫-台中",
      "buyVol": 54,
      "sellVol": 604,
      "netSell": 550,
      "pct": 1.16
    },
    {
      "broker": "元大-淡水",
      "buyVol": 1,
      "sellVol": 503,
      "netSell": 502,
      "pct": 1.06
    },
    {
      "broker": "光和-高雄",
      "buyVol": 0,
      "sellVol": 460,
      "netSell": 460,
      "pct": 0.97
    },
    {
      "broker": "元大-永春",
      "buyVol": 2,
      "sellVol": 456,
      "netSell": 454,
      "pct": 0.96
    },
    {
      "broker": "國泰-台南",
      "buyVol": 1,
      "sellVol": 424,
      "netSell": 423,
      "pct": 0.89
    },
    {
      "broker": "華南永昌-古亭",
      "buyVol": 0,
      "sellVol": 420,
      "netSell": 420,
      "pct": 0.89
    },
    {
      "broker": "富邦-新板",
      "buyVol": 7,
      "sellVol": 425,
      "netSell": 418,
      "pct": 0.88
    },
    {
      "broker": "富邦-永和",
      "buyVol": 0,
      "sellVol": 404,
      "netSell": 404,
      "pct": 0.85
    },
    {
      "broker": "統一-台中",
      "buyVol": 0,
      "sellVol": 402,
      "netSell": 402,
      "pct": 0.85
    },
    {
      "broker": "合庫-嘉義",
      "buyVol": 1,
      "sellVol": 381,
      "netSell": 380,
      "pct": 0.8
    },
    {
      "broker": "元大-四維",
      "buyVol": 4,
      "sellVol": 383,
      "netSell": 379,
      "pct": 0.8
    },
    {
      "broker": "元大-草屯",
      "buyVol": 12,
      "sellVol": 377,
      "netSell": 365,
      "pct": 0.77
    }
  ],
  "totalBuyVol": 36245,
  "totalSellVol": 7902,
  "avgBuyCost": 24.95,
  "avgSellCost": 24.91
}